mcs_kfold/__init__.py
mcs_kfold/mcs_kfold.py
mcs_kfold-0.1.1.dist-info/LICENSE
mcs_kfold-0.1.1.dist-info/WHEEL
mcs_kfold-0.1.1.dist-info/METADATA
mcs_kfold-0.1.1.dist-info/RECORD
