Metadata-Version: 2.1
Name: mcs-kfold
Version: 0.1.1
Summary: 
License: MIT
Author: Masashi Sode
Author-email: masashi.sode@gmail.com
Requires-Python: >=3.6.5,<4.0.0
Classifier: License :: OSI Approved :: MIT License
Classifier: Programming Language :: Python :: 3
Classifier: Programming Language :: Python :: 3.7
Classifier: Programming Language :: Python :: 3.8
Classifier: Programming Language :: Python :: 3.9
Requires-Dist: numpy (>=1.19.1,<2.0.0)
Requires-Dist: pandas (>=1.1.1,<2.0.0)
Requires-Dist: scikit-learn (>=0.23.2,<0.24.0)
Requires-Dist: scipy (>=1.5.2,<2.0.0)
